PyToNotion/__init__.py
PyToNotion/pyNotion.py
pytonotion-0.0.1.dist-info/METADATA
pytonotion-0.0.1.dist-info/WHEEL
pytonotion-0.0.1.dist-info/licenses/LICENSE.txt
pytonotion-0.0.1.dist-info/RECORD
