Metadata-Version: 2.3
Name: PyToNotion
Version: 0.0.1
Summary: Notion API with Python
Project-URL: Homepage, https://github.com/Navi-SS/PyToNotion
Project-URL: Bug Tracker, https://github.com/Navi-SS/PyToNotion/issues
Author-email: vania_vaniusha <ivan.castaneda.nazario@gmail.com>
License: MIT License
Classifier: License :: OSI Approved :: MIT License
Classifier: Operating System :: OS Independent
Classifier: Programming Language :: Python :: 3
Requires-Python: >=3.5
Requires-Dist: requests>=2.28
